{"forum": {"content": "\u65b0\u624b\u4e0a\u8def", "images": ["http://filestoresg1.beetalkmobile.com:8081/file/f85df1681e85c605d40a052d775474cf", "http://filestoresg1.beetalkmobile.com:8081/file/435a3ba16a0528d3a41ec65becc53b17", "http://filestoresg1.beetalkmobile.com:8081/file/db8e486178c39c3d90ef9369964fc2e3", "http://filestoresg1.beetalkmobile.com:8081/file/a054d5d7ed502485fdd9497675584a2f", "http://filestoresg1.beetalkmobile.com:8081/file/1e51b27c5a2c7df5062f4b7e15780793", "http://filestoresg1.beetalkmobile.com:8081/file/6ff823ffa71f1dec093190cdbf85346a"], "urls": [], "title": "\u525b\u5b78\u963f"}, "threadStatus": 0, "regionId": 886, "barStatus": 0, "barId": 77, "postBy": {"utc": 1464711757000, "level": 2, "location": "\u6843\u5712\u5e02\u00b7\u53f0\u7063", "avatar": "http://filestoresg1.beetalkmobile.com:8081/file/1219498035704045571", "name": "\ud83d\ude0e"}, "id": 3830502}
