{"forum": {"content": "Id:Beedong_\u5509\u5466<br />\u6709mic\u4f73\u4e00\u8d77\u73a9\u5c31\u662f\u8981\u6b61\u6a02\u6211\u6709\u9ede\u8052\u566a\u54c8\u54c8<br />\u767d\u91d1\u96f7\u96f7\ud83d\ude2d\ud83d\ude2d\u5225\u5acc\u68c4\u6211<br />Ng rk ar\u52a0\u6211\u4e00\u8d77\u73a9", "images": ["http://filestoresg1.beetalkmobile.com:8081/file/98efbd8d82cfadcc72677d78fb183d62"], "urls": [], "title": "\u7121\u804a\u4e00\u8d77\u6253lol"}, "threadStatus": 1, "regionId": 886, "barStatus": 0, "barId": 60, "postBy": {"utc": 1463508451000, "level": 3, "location": "\u6843\u5712\u5e02\u00b7\u53f0\u7063", "avatar": "http://filestoresg1.beetalkmobile.com:8081/file/-3500401902860922354", "name": "\u2600\ufe0f\u2600\ufe0f"}, "id": 3740157}
