{"forum": {"content": "\u54c8\u54c8\u5176\u5be6\u5c31\u53ea\u662f\u55ae\u8eab\u5566\uff01<br />", "images": ["http://filestoresg1.beetalkmobile.com:8081/file/86646900f6c646540b822cc2b1b2fd29", "http://filestoresg1.beetalkmobile.com:8081/file/a75dbf460fcb4a21bb1fd61a56c25f33"], "urls": [], "title": "\u6c92\u4ec0\u9ebc \u8ddf\u5927\u90e8\u5206\u4eba\u4e00\u6a23"}, "threadStatus": 0, "regionId": 886, "barStatus": 0, "barId": 205, "postBy": {"utc": 1464336298000, "level": 1, "location": "", "avatar": "http://filestoresg1.beetalkmobile.com:8081/file/-7810613931003092630", "name": "\u767d"}, "id": 3801877}
