{"forum": {"content": "\u5403\u904e\u7684\u90fd\u8aaa\u597d\u5403\u5537\uff01\u5c24\u5176\u662f\u7117\u70e4\u767e\u5143\u6709\u627e\u5537", "images": ["http://filestoresg1.beetalkmobile.com:8081/file/f0b0e5b8df1346e9f59dc5665f693198", "http://filestoresg1.beetalkmobile.com:8081/file/f712e21fae5ec2906f77f9bd890bd7f9", "http://filestoresg1.beetalkmobile.com:8081/file/d278ca7b499b917111c9eac294bb0cb6", "http://filestoresg1.beetalkmobile.com:8081/file/1ddbd9ab5d936b128bf4cad9585395a0", "http://filestoresg1.beetalkmobile.com:8081/file/352194f0a7989b5e761bb9ed609d0ef5", "http://filestoresg1.beetalkmobile.com:8081/file/67c9634e3ca8a7d4c3b89ccbcb63ee58"], "urls": [], "title": "\u60f3\u5690\u5690\u7f8e\u5473\u7684\u9285\u677f\u7fa9\u5927\u5229\u9eb5\u55ce\uff0c\u7167\u904e\u4f86\u5c31\u5c0d\u4e86"}, "threadStatus": 0, "regionId": 886, "barStatus": 0, "barId": 98, "postBy": {"utc": 1460704214000, "level": 3, "location": "\u65b0\u5317\u5e02\u00b7\u53f0\u7063", "avatar": "http://filestoresg1.beetalkmobile.com:8081/file/1772741501520096219", "name": "\u98fe\u98fe\u770b\u9577\u671f\u52de\u5de5"}, "id": 3518074}
