{"forum": {"content": "\u54c8\u54c8\u54c8\uff0c\u56e0\u70ba\u6709\u8caa\u5403\u7684\u4e3b\u4eba<br />\u6240\u4ee5\u90fd\u53d6\u98df\u7269\u7684\u540d\u5b57<br /><br />\u5976\u6cb9\uff08\u767d\u8c93\u7537\u751f\uff09<br />\u58a8\u9b5a\uff08\u9ed1\u8c93\u5973\u751f\uff09<br />\u9eb5\uff08\u6a58\u8c93\u7537\u751f\uff09<br /><br />\u4e4b\u5f8c\u5982\u679c\u518d\u8a8d\u990a\u7684\uff0c\u7e7c\u7e8c\u52a0\u5165\u83dc\u55ae\u5167", "images": ["http://filestoresg1.beetalkmobile.com:8081/file/c8f34bb486039c30d9fbf63663f6e82c", "http://filestoresg1.beetalkmobile.com:8081/file/fe1b1857a6cd028f5bf19b90dc6685cf", "http://filestoresg1.beetalkmobile.com:8081/file/3e0cb8304eddecf1bedb09a017acb8bf", "http://filestoresg1.beetalkmobile.com:8081/file/ad2caa346d7cd5e1df12193ce9acd3ec"], "urls": [], "title": "\u9910\u5ef3\u958b\u5e55\u4e86\uff01\uff01"}, "threadStatus": 0, "regionId": 886, "barStatus": 0, "barId": 751, "postBy": {"utc": 1466086368000, "level": 8, "location": "\u9ad8\u96c4\u5e02\u00b7\u53f0\u7063", "avatar": "http://filestoresg1.beetalkmobile.com:8081/file/4328988403327633648", "name": " \ud83c\udf38Nina \u5c0f\u5149\ud83d\udc95"}, "id": 3932210}
