{"forum": {"content": "3\u500b\u7f8e\u5973<br />\u4e00\u4f4d \u539f\u4f4f\u6c11<br />\u4e00\u4f4d \u99ac\u4f86\u897f\u4e9e<br />\u4e00\u4f4d \u81ea\u4ee5\u70ba\u662f\u539f\u4f4f\u6c11\u7684\u5e73\u5730\u4eba<br />\u54c8\u54c8\u54c8", "images": ["http://filestoresg1.beetalkmobile.com:8081/file/83c15db729d96f8efea5826db1afa580", "http://filestoresg1.beetalkmobile.com:8081/file/08f2aeb46966ed5d4801c6dda9b72344", "http://filestoresg1.beetalkmobile.com:8081/file/bd14863e6216f4afa68373d95281c0e4", "http://filestoresg1.beetalkmobile.com:8081/file/89b39c2c29ef7b59d27b3c9c0c6d0f15", "http://filestoresg1.beetalkmobile.com:8081/file/2ef5933a3f656aea9ccf0cfb3931fb34", "http://filestoresg1.beetalkmobile.com:8081/file/d61c5a1f3131a60bc8ffe53b317fe283"], "urls": [], "title": "\u6350\u8840\u5fd7\u5de5"}, "threadStatus": 0, "regionId": 886, "barStatus": 0, "barId": 77, "postBy": {"utc": 1458316029000, "level": 10, "location": "\u65b0\u5317\u5e02\u00b7\u53f0\u7063", "avatar": "http://filestoresg1.beetalkmobile.com:8081/file/6116129103904095277", "name": "\u522a\u5e33\u865f"}, "id": 3329317}
