{"forum": {"content": "\u6b63\u5728\u6478\u7d22\u4e2d\uff0c\uff0c\uff0c\uff0c", "images": ["http://filestoresg1.beetalkmobile.com:8081/file/2c2c8219dbf20140f046a7db0da2550d"], "urls": [], "title": "\u597d\u4e45\u6c92\u78b0\uff0c\uff0c\uff0c(\u9700\u8981\u6478\u7d22\uff0c\uff0c\uff0c"}, "threadStatus": 0, "regionId": 886, "barStatus": 0, "barId": 205, "postBy": {"utc": 1462102424000, "level": 1, "location": "\u53f0\u5357\u5e02\u00b7\u53f0\u7063", "avatar": "http://filestoresg1.beetalkmobile.com:8081/file/2018360302870311208", "name": "\u5f9e\u5fc3\u958b\u59cb"}, "id": 3629288}
