{"forum": {"content": "\u4e09\u91cd\u5546\u5de5  \u677f\u91d1\u79d1", "images": ["http://filestoresg1.beetalkmobile.com:8081/file/6fa2378e340eee1efadfe01bfb38c46c", "http://filestoresg1.beetalkmobile.com:8081/file/2e9937a532b028699783b65490b30b35", "http://filestoresg1.beetalkmobile.com:8081/file/ff861a21fdd41c7920c74cf2199b4be1"], "urls": [], "title": "\u5fb5\u5973\u53cb"}, "threadStatus": 0, "regionId": 886, "barStatus": 0, "barId": 438, "postBy": {"utc": 1458170907000, "level": 3, "location": "\u65b0\u5317\u5e02\u00b7\u53f0\u7063", "avatar": "http://filestoresg1.beetalkmobile.com:8081/file/-6038053856725627982", "name": "\u21a9\u5091\u5bf6\u21aa"}, "id": 3317187}
