{"forum": {"content": "\u904e\u5e74\u5be6\u5728\u662f\u6709\u9ede\u7121\u8da3\u554a\u2026<br />\u9577\u8f29\u90fd\u554f\u4e00\u4e9b\u5c37\u5c2c\u7684\u554f\u984c\uff0c<br />\u6709\u6c92\u6709\u4eba\u9858\u610f\u52a0\u500b\u8cf4\u804a\u5929\u7684<br />\u6709\u8ab0\u60f3\u8981\u4ea4\u500b\u670b\u53cb\u804a\u5929\u6253\u767c\u6642\u9593\u7684\u55ceXD?", "images": ["http://filestoresg1.beetalkmobile.com:8081/file/25511126fccb85ac7a606f868a36ddbe"], "urls": [], "title": "\u55ae\u8eab\u597d\u7121\u804a\u2026"}, "threadStatus": 1, "regionId": 886, "barStatus": 0, "barId": 205, "postBy": {"utc": 1454866520000, "level": 2, "location": "\u65b0\u5317\u5e02\u00b7\u53f0\u7063", "avatar": "http://filestoresg1.beetalkmobile.com:8081/file/-5258604567274214396", "name": "\u9716.\u270c\ufe0f"}, "id": 3058734}
