{"forum": {"content": "\u9019\u88e1\u7537\u751f\u7684\u6bd4\u4f8b\u6709\u6c92\u6bd4\u5973\u751f\u591a\u554a\u554a\u554a<br />\u7559\u500b\u8a00\u676f \u7b2c\u4e00\u6b21\u73a9\u7d66\u500b\u9762\u5b50\u676f\ud83d\ude02\ud83d\ude02<br />Po\u9019\u6587\u883b\u9700\u8981\u52c7\u6c23Der \u54c8\u54c8<br />\u7537\u751f+1<br />\u5973\u751f+2", "images": ["http://filestoresg1.beetalkmobile.com:8081/file/7cacf06e2683fa0b6348cb5856935830"], "urls": [], "title": "\u9ad8\u4e09\u3002"}, "threadStatus": 0, "regionId": 886, "barStatus": 0, "barId": 438, "postBy": {"utc": 1460912200000, "level": 2, "location": "\u5f70\u5316\u7e23\u00b7\u53f0\u7063", "avatar": "http://filestoresg1.beetalkmobile.com:8081/file/7339888828482858006", "name": "\u5fae\u91ba\ud83d\ude0f\ud83d\ude0f"}, "id": 3534887}
