{"forum": {"content": "\u4f60\u4e5f\u6703\u5b88\u8457\u79d8\u5bc6\u4e0d\u80af\u544a\u8a34\u6211..<br /><br /><br />\u8016\u4f60\u5abd\u611b\u60c5\uff01", "images": ["http://filestoresg1.beetalkmobile.com:8081/file/3acd4c3af940983ef4497fcb21631523"], "urls": [], "title": "\u4f60\u4e5f\u6703\u611b\u4e0a\u4e00\u500b\u4eba\u4ed8\u51fa\u5f88\u591a\u5f88\u591a"}, "threadStatus": 0, "regionId": 886, "barStatus": 0, "barId": 13, "postBy": {"utc": 1456777136000, "level": 1, "location": "", "avatar": "http://filestoresg1.beetalkmobile.com:8081/file/-8244055709037209851", "name": "\u0178 \u2604\u4f60\u771f\u4ed6\u5abd\u96e3\u627e"}, "id": 3208277}
