{"forum": {"content": "\u5404\u4f4d\u90fd\u600e\u9ebc\u8868\u73fe\u5462", "images": ["http://filestoresg1.beetalkmobile.com:8081/file/a88682f6551a6940a0eae17782ad8947"], "urls": [], "title": "\u7f8e\u8853\u8ab2 \u984c\u76ee \u756b\u6211\u6700\u597d\u7684\u670b\u53cb"}, "threadStatus": 0, "regionId": 886, "barStatus": 0, "barId": 33, "postBy": {"utc": 1464751065000, "level": 1, "location": "\u53f0\u5317\u5e02\u00b7\u53f0\u7063", "avatar": "http://filestoresg1.beetalkmobile.com:8081/file/-3260016790416474286", "name": "\u7cbe\u7dfb\u6d17\u8863"}, "id": 3832417}
