{"forum": {"content": "\u70ba\u4ec0\u9ebc\u5f88\u591a\u4eba\u90fd\u8aaa\u6211\u50cf\uff11\uff17.\uff11\uff18\u6b72<br /><br />\u53ef\u662f\u6211\u5df2\u7d93\u6211\uff12\uff11\u4e86\u8036\ud83d\ude02", "images": ["http://filestoresg1.beetalkmobile.com:8081/file/7d152a5541a95e995c874a6ba88e6ecb", "http://filestoresg1.beetalkmobile.com:8081/file/36bf88226a0659950cb406dd5e673c33", "http://filestoresg1.beetalkmobile.com:8081/file/29873e5d3ed8bebbb81dcd29e597d106", "http://filestoresg1.beetalkmobile.com:8081/file/67d1fd775f85f82782b028a6b56c15f2"], "urls": [], "title": "\u5c0f\u5f1f\u5f1f\ud83d\ude09"}, "threadStatus": 0, "regionId": 886, "barStatus": 0, "barId": 734, "postBy": {"utc": 1456035514000, "level": 1, "location": "\u53f0\u4e2d\u5e02\u00b7\u53f0\u7063", "avatar": "http://filestoresg1.beetalkmobile.com:8081/file/-727908582250088448", "name": "\u5289\u6e05."}, "id": 3148058}
