{"forum": {"content": "\u5973\u751f\u90fd\u559c\u6b61\u88ab\u966a\u4f34\uff01<br />\u59ca\u59ca\u9084\u6bd4\u8f03\u6703\u9ad4\u8ad2\uff01<br />\u7537\u751f\u81ea\u5df1\u4e0d\u61c2\u5b89\u5b9a\uff01<br />\u4ea4\u5e74\u9f61\u5c0f\u7684\u5206\u66f4\u5feb\uff01<br />\u7537\u5973\u76f8\u8655\u8981\u8b1b\u4e92\u76f8\uff01<br />\u6c92\u5fc3\u7dad\u6301\u7684\u5c31\u5225\u88dd\uff01", "images": ["http://filestoresg1.beetalkmobile.com:8081/file/81b5ab765271eb2fb8cdcd6205178038", "http://filestoresg1.beetalkmobile.com:8081/file/cbd0946d17929d18a1954bd25d9ac2f9", "http://filestoresg1.beetalkmobile.com:8081/file/6aefdf742c3b11c8357d947f9fa020c3", "http://filestoresg1.beetalkmobile.com:8081/file/218d34e7603903e820e50721f328f93b"], "urls": [], "title": "\u70ba\u4f55\u73fe\u5728\u90a3\u9ebc\u591a\u5f1f\u6200\u59ca\uff1f"}, "threadStatus": 0, "regionId": 886, "barStatus": 0, "barId": 734, "postBy": {"utc": 1461459627000, "level": 8, "location": "\u65b0\u5317\u5e02\u00b7\u53f0\u7063", "avatar": "http://filestoresg1.beetalkmobile.com:8081/file/-2651439297475123572", "name": "\u8292\u679c\ud83d\udc1d"}, "id": 3579088}
