{"forum": {"content": "\u54c8\u56c9\uff01\u310e", "images": ["http://filestoresg1.beetalkmobile.com:8081/file/d09e6ebe315b0c8e43466d2ab070d981", "http://filestoresg1.beetalkmobile.com:8081/file/3a25a30fb5d48d18e7d02214057ffe9e", "http://filestoresg1.beetalkmobile.com:8081/file/a37b05a47f446966d7dac9cf73019a0f"], "urls": [], "title": "\u5927\u5bb6\u597d"}, "threadStatus": 0, "regionId": 886, "barStatus": 0, "barId": 205, "postBy": {"utc": 1460485410000, "level": 1, "location": "\u5357\u6295\u7e23\u00b7\u53f0\u7063", "avatar": "http://filestoresg1.beetalkmobile.com:8081/file/2837475520519547604", "name": "\u67c4\u6953"}, "id": 3503028}
