{"forum": {"content": "\u904e\u6163\u4e86\u90fd\u5e02\u751f\u6d3b\uff01<br />\u770b\u904d\u4e86\u4e16\u9593\u51b7\u6696\uff01<br />\u4ea4\u904e\u4e86\u7537\u5973\u670b\u53cb\uff01<br />\u9084\u662f\u89ba\u5f97\u60a8\u5011\u597d\uff01<br />\u6a02\u5929\u958b\u6717\u611b\u641e\u7b11\uff01<br />\u5c31\u7b97\u82e6\u4e5f\u809a\u88e1\u541e\uff01<br />\u8a8d\u8b58\u60a8\u5011\u771f\u662f\u597d\uff01", "images": ["http://filestoresg1.beetalkmobile.com:8081/file/1973801f5f65d7a9bc6e89166f6ce0a9"], "urls": [], "title": "\u539f\u4f4f\u6c11\u7684\u670b\u53cb\u60a8\u597d"}, "threadStatus": 0, "regionId": 886, "barStatus": 0, "barId": 727, "postBy": {"utc": 1455834520000, "level": 2, "location": "", "avatar": "http://filestoresg1.beetalkmobile.com:8081/file/-4906785027962509278", "name": "\u66f8\u5230\u7528\u6642\u65b9\u6068\u5c11"}, "id": 3132481}
