{"forum": {"content": "\u804a\u5929\uff5e", "images": ["http://filestoresg1.beetalkmobile.com:8081/file/ceef4c774e26be5c93c16af25a717d75", "http://filestoresg1.beetalkmobile.com:8081/file/4fcbb151d66c594b019e6de3d4be5274"], "urls": [], "title": "Hi"}, "threadStatus": 1, "regionId": 886, "barStatus": 0, "barId": 205, "postBy": {"utc": 1457193326000, "level": 1, "location": "\u65b0\u5317\u5e02\u00b7\u53f0\u7063", "avatar": "http://filestoresg1.beetalkmobile.com:8081/file/934487034566375169", "name": "Jason"}, "id": 3239784}
