{"forum": {"content": "\u9019\u300c\u7de3\u300d\u597d\u96e3\u627e\u554a\uff5e!", "images": ["http://filestoresg1.beetalkmobile.com:8081/file/be86ffed9f9b3116bb2d3978eb3a3a7a"], "urls": [], "title": "\u751f\u65e5\u8981\u904e\u4e86\u22ef"}, "threadStatus": 0, "regionId": 886, "barStatus": 0, "barId": 734, "postBy": {"utc": 1456672208000, "level": 7, "location": "\u53f0\u5317\u5e02\u00b7\u53f0\u7063", "avatar": "http://filestoresg1.beetalkmobile.com:8081/file/-1292059202672635645", "name": "\u8521\u8521\u8521"}, "id": 3199849}
