{"forum": {"content": "\u967d\u5149\u4e0d\u967d\u5149> <", "images": ["http://filestoresg1.beetalkmobile.com:8081/file/1025b7124ada88afeee083554cce62a7", "http://filestoresg1.beetalkmobile.com:8081/file/2091a51c05d17d2d71514af61396e825", "http://filestoresg1.beetalkmobile.com:8081/file/6e6ea4b0340ceaed3ff4d696af6f506c", "http://filestoresg1.beetalkmobile.com:8081/file/c1f18fc0acc3501cf9fa47d982b35454", "http://filestoresg1.beetalkmobile.com:8081/file/2142d03e55bcb93ada5d4c4ec7853bcb"], "urls": [], "title": "73/09/22"}, "threadStatus": 0, "regionId": 886, "barStatus": 0, "barId": 765, "postBy": {"utc": 1458145779000, "level": 0, "location": "\u65b0\u5317\u5e02\u00b7\u53f0\u7063", "avatar": "http://filestoresg1.beetalkmobile.com:8081/file/2141990494748473862", "name": "\u8981\u79fb\u9664\u56c9\u871c\u8702\uff0csee you~"}, "id": 3315965}
