{"forum": {"content": "\u5973\u751f\u4f7f\u7528\u9999\u6c34\u66f4\u6027\u611f\u8acb\u5927\u5bb6\u804a\u804a\u3002", "images": ["http://filestoresg1.beetalkmobile.com:8081/file/4a98da132a50f7e7db6ac7ec820a1c80", "http://filestoresg1.beetalkmobile.com:8081/file/307f466fba6b6f36ea86211fe793bf67", "http://filestoresg1.beetalkmobile.com:8081/file/958ba48a64b54059fa6c4370b782e278"], "urls": [], "title": "\u5973\u4eba\u9999\uff0c\u559c\u611b\u4f7f\u7528\u9999\u6c34\u7684\u7f8e\u5973\uff0c\u7537\u751f\u559c\u611b\u805e\u5973\u751f\u7684\u9999\u6c34\u5473\u55ce"}, "threadStatus": 0, "regionId": 886, "barStatus": 0, "barId": 422, "postBy": {"utc": 1458263891000, "level": 0, "location": "\u5b9c\u862d\u7e23\u00b7\u53f0\u7063", "avatar": "http://filestoresg1.beetalkmobile.com:8081/file/7808029009044410213", "name": "\u5143\u65e6"}, "id": 3324504}
