{"forum": {"content": "\u524d\u5e7e\u5929\u62ff\u8d77\u706b\u96de\u7a81\u7136\u60f3\u5230\uff0c\u706b\u7130\u5230\u5e95\u4ec0\u9ebc\u984f\u8272\u6700\u71d9\u6eab\u5ea6\u6700\u9ad8\ud83d\ude10\ud83d\ude10<br />\u5230\u5e95\u662f\u85cd\u8272\u9084\u662f\u7d05\u8272", "images": ["http://filestoresg1.beetalkmobile.com:8081/file/2112e7fa74aa156c71d345b830d13bb6"], "urls": [], "title": "\u706b\u7130\u5230\u5e95\u4ec0\u9ebc\u984f\u8272\u6700\u71d9"}, "threadStatus": 0, "regionId": 886, "barStatus": 0, "barId": 422, "postBy": {"utc": 1457179593000, "level": 2, "location": "\u9ad8\u96c4\u5e02\u00b7\u53f0\u7063", "avatar": "http://filestoresg1.beetalkmobile.com:8081/file/-114694441867897190", "name": "\u79d1\u79d1"}, "id": 3238242}
