{"forum": {"content": "\u4e00\u5e74\u534a\u5c31\u9019\u6a23\u6c92\u4e86<br />\u6211\u5011\u76f8\u611b\u7684\u4e00\u5207 \u73fe\u5728\u53ea\u662f\u56de\u61b6<br />\u771f\u7684\u7d50\u675f\u4e86\u3002", "images": ["http://filestoresg1.beetalkmobile.com:8081/file/030d625c67ef2c5209d83b96cd691f67"], "urls": [], "title": "\u4f60\u4e5f\u6210\u70ba\u904e\u53bb\u4e86"}, "threadStatus": 0, "regionId": 886, "barStatus": 0, "barId": 18, "postBy": {"utc": 1465953027000, "level": 4, "location": "\u9ad8\u96c4\u5e02\u00b7\u53f0\u7063", "avatar": "http://filestoresg1.beetalkmobile.com:8081/file/7896657332370020241", "name": "A Sa"}, "id": 3921698}
