{"forum": {"content": "\u89d2\u5ea6\u6293\u597d\u6bcf\u4e00\u5f35\u7167\u7247\u90fd\u5f88\u597d\u770b<br />\u4f46\u6211\u7e3d\u662f\u62ff\u5fc3\u60c5\u4e0d\u597d\u6642\u53bb\u62cd\u624d\u597d<br />\u62cd\u7167\u6c92\u6709\u5206\u559c\u6012\u54c0\u6a02<br />\u611f\u89ba\u4f86\u4e86<br />\u5c31\u662f\u62cd", "images": ["http://filestoresg1.beetalkmobile.com:8081/file/efc8c6b539acd1226f5a418536c2daa8", "http://filestoresg1.beetalkmobile.com:8081/file/da6ebbd3c1225139980176e3300cdd1f", "http://filestoresg1.beetalkmobile.com:8081/file/1106f86cab79f5320150e41d082de7d6", "http://filestoresg1.beetalkmobile.com:8081/file/4091454b5dfd0ffa979909de635f1b0f", "http://filestoresg1.beetalkmobile.com:8081/file/65ad6165e41d067d6657f84c8d2cc2c3", "http://filestoresg1.beetalkmobile.com:8081/file/af390b8c667bb326cb12eda13107e6d6"], "urls": [], "title": "\u6211\u8001\u5be6\u8b1b\u6211\u6eff\u7167\u9a19\u7684"}, "threadStatus": 0, "regionId": 886, "barStatus": 0, "barId": 4, "postBy": {"utc": 1455349631000, "level": 3, "location": "\u9ad8\u96c4\u5e02\u00b7\u53f0\u7063", "avatar": "http://filestoresg1.beetalkmobile.com:8081/file/6166908935021251733", "name": "\u6708"}, "id": 3093494}
