{"forum": {"content": "\u5be6\u5e97\u5728\u4e09\u7fa9\u6728\u96d5\u535a\u7269\u9928\u65c1<br /><br />\u76c6\u683d<br /><br />\u5ead\u5712\u6a39<br /><br />\u85dd\u8853\u54c1<br /><br />", "images": ["http://filestoresg1.beetalkmobile.com:8081/file/b927914e3f31e7aa4794e9a65d5de921", "http://filestoresg1.beetalkmobile.com:8081/file/b5d2e07e1a701724c0be40ff586d8e24", "http://filestoresg1.beetalkmobile.com:8081/file/0392e05adc3ed78656893eb870289b3c", "http://filestoresg1.beetalkmobile.com:8081/file/f3cf1fbf0e2ebb14c6fdbef525a15b4f"], "urls": [], "title": "\u6709\u9322\u4eba\u73a9\u85dd\u8853\u54c1"}, "threadStatus": 1, "regionId": 886, "barStatus": 2, "barId": 788, "postBy": {"utc": 1459998149000, "level": 3, "location": "\u9ad8\u96c4\u5e02\u00b7\u53f0\u7063", "avatar": "http://filestoresg1.beetalkmobile.com:8081/file/4649667563790427229", "name": "\u7b49\u4e00\u500b\u4eba~\u5496\u5561"}, "id": 3463823}
