{"forum": {"content": "74\u5e74\u6b21 180\u516c\u5206 73\u516c\u65a4 \u7a69\u5b9a\u5de5\u4f5c <br /><br />\u4e0d\u62bd\u7159 \u5c0f\u914c \u7121\u4e0d\u826f\u55dc\u597d<br /><br />\u5929\u79e4\u7537  \u7d66\u500b\u6a5f\u6703\u5427<br /><br /><br /><br />", "images": ["http://filestoresg1.beetalkmobile.com:8081/file/2a1f894ebf89692c6d76563b609798ba"], "urls": [], "title": "\u7576\u7136\u5fb5\u5a5a\u560d"}, "threadStatus": 0, "regionId": 886, "barStatus": 0, "barId": 740, "postBy": {"utc": 1462288869000, "level": 10, "location": "\u53f0\u5357\u5e02\u00b7\u53f0\u7063", "avatar": "http://filestoresg1.beetalkmobile.com:8081/file/-8291078534563219552", "name": "\u653f\u8473"}, "id": 3644398}
