{"forum": {"content": "\u660e\u5929\u53c8\u8981\u596e\u529b\u5de5\u4f5c\u4e86\ud83d\ude2d", "images": ["http://filestoresg1.beetalkmobile.com:8081/file/6feee6a86998affc379ae083838d8e6e", "http://filestoresg1.beetalkmobile.com:8081/file/4f0dae7e20ddb73d8ee1a5dc16a95357", "http://filestoresg1.beetalkmobile.com:8081/file/299027b3d6925ce1befc9584c4b80f6c", "http://filestoresg1.beetalkmobile.com:8081/file/155ef447f18e0e5565e8ad10085b93e0", "http://filestoresg1.beetalkmobile.com:8081/file/e640ef6227535e1792d84daea88944fa"], "urls": [], "title": "\u51fa\u904a"}, "threadStatus": 0, "regionId": 886, "barStatus": 0, "barId": 4, "postBy": {"utc": 1462194229000, "level": 9, "location": "", "avatar": "http://filestoresg1.beetalkmobile.com:8081/file/7566155131124814336", "name": "Hannah*\u82b1\u82b1"}, "id": 3636554}
