{"forum": {"content": "\u5357\u65b9\u6fb3\u6e2f\u53e3", "images": ["http://filestoresg1.beetalkmobile.com:8081/file/b244df60fcefea803b8230fd4cff6e07", "http://filestoresg1.beetalkmobile.com:8081/file/f34c236eba4932815af8dcb377a82c82", "http://filestoresg1.beetalkmobile.com:8081/file/9d819485c738097dc87edc9ec6499f36"], "urls": [], "title": "\u9084\u597d\u9b5a\u6709\u5403"}, "threadStatus": 0, "regionId": 886, "barStatus": 0, "barId": 723, "postBy": {"utc": 1463342704000, "level": 7, "location": "\u5b9c\u862d\u7e23\u00b7\u53f0\u7063", "avatar": "http://filestoresg1.beetalkmobile.com:8081/file/-7652372223391561091", "name": "\u5fb7"}, "id": 3727199}
