{"forum": {"content": "\u4e0d\u7528\u60f3\u2026\u624b\u6a5f\u62cd\u651d\u5148", "images": ["http://filestoresg1.beetalkmobile.com:8081/file/2d776ecac8ecedd120513212ae36cac8", "http://filestoresg1.beetalkmobile.com:8081/file/a506ee57e128e0db866542977543f29b", "http://filestoresg1.beetalkmobile.com:8081/file/e2605b1241d901f013b68d90eb860e22", "http://filestoresg1.beetalkmobile.com:8081/file/f2492bb573159e12b82ac5c578fd4e52", "http://filestoresg1.beetalkmobile.com:8081/file/a3858c9dc45e75ab668ddc9df66f8d6d", "http://filestoresg1.beetalkmobile.com:8081/file/dd3270acd456caa5670d325972fc3dc0"], "urls": [], "title": "[\u624b\u6a5f\u62cd\u651d] \u5de5\u4f5c\u9047\u4e0a"}, "threadStatus": 0, "regionId": 886, "barStatus": 0, "barId": 77, "postBy": {"utc": 1458494280000, "level": 33, "location": "\u5357\u6295\u7e23\u00b7\u53f0\u7063", "avatar": "http://filestoresg1.beetalkmobile.com:8081/file/6102071832975644010", "name": "\u7ff0\u7433"}, "id": 3344119}
