{"forum": {"content": "\u3010\u51fa\u552e\u3011i Phone6 4.7\u540b 64g \u91d1\u8272<br />\u3010\u50f9\u9322\u3011$14000\uff08\u4e0d\u4e8c\u50f9\uff09<br />\u3010\u72c0\u6cc1\u3011\u5916\u89c08\u6210\u65b0\uff0c\u4f7f\u7528\u529f\u80fd\u826f\u597d<br />\uff08\u53bb\u5e74\u4e09\u6708\u5230\u73fe\u5728\uff0c\u76d2\u5b50\u9084\u5728\uff09<br />\u3010\u4fdd\u56fa\u3011\u5feb\u904e\u4fdd<br />\u3010\u914d\u4ef6\u3011\u539f\u5ee0\u624b\u6a5f*1\u3001\u5168\u65b0\u9ad8\u6e05\u8cbc\u819c*1<br />\u3010\u4ea4\u6613\u3011\u79c1\u8a0a", "images": ["http://filestoresg1.beetalkmobile.com:8081/file/9308589dbb44accf3eddfbeb7184886f", "http://filestoresg1.beetalkmobile.com:8081/file/933ef7d93d75555988e75ad1559340af", "http://filestoresg1.beetalkmobile.com:8081/file/2fac7b254d8f5ae00516c815d92e8b7c", "http://filestoresg1.beetalkmobile.com:8081/file/e9db2deaa43ca0e4b2e4491694943d04", "http://filestoresg1.beetalkmobile.com:8081/file/e47ddbd911ebdc1dbd0fea6e5503d073", "http://filestoresg1.beetalkmobile.com:8081/file/8669a7a7ad38287b9886487a58a9ca79"], "urls": [], "title": "\u8ce3i6"}, "threadStatus": 1, "regionId": 886, "barStatus": 0, "barId": 74, "postBy": {"utc": 1462495328000, "level": 1, "location": "\u6843\u5712\u5e02\u00b7\u53f0\u7063", "avatar": "http://filestoresg1.beetalkmobile.com:8081/file/-7862263486882291711", "name": "Line"}, "id": 3659652}
