{"forum": {"content": "\u672c\u5c0a\u947d5 \u672c\u5c0a\u6709\u65e5\u6587\u8981\u52a0\u7559ID\u7d66\u6211~<br />\u5c0f\u865f\u76ee\u524d\u5341\u4e09\u9023\u52dd\u5728\u767d3 29\u5206<br />\u60f3\u627e\u6b61\u6a02\u7684ng\u968a\u53cb<br />\u958b\u5fc3\u73a9\u904a\u6232\u6700\u91cd\u8981<br />\u4f86\u8ddf\u6211\u4e00\u8d77\u73a9\u3105", "images": ["http://filestoresg1.beetalkmobile.com:8081/file/222f39ade0236a02c26ee940de2ccc73", "http://filestoresg1.beetalkmobile.com:8081/file/edbcb1f6154f497e910a41f276e5d16a", "http://filestoresg1.beetalkmobile.com:8081/file/0869b93a93c1f1b059f29f770bafb76c", "http://filestoresg1.beetalkmobile.com:8081/file/e5a5e1aa98da412c9d1d9b817f44e0f9"], "urls": [], "title": "\u4ea4\u670b\u53cb\u5427"}, "threadStatus": 0, "regionId": 886, "barStatus": 0, "barId": 60, "postBy": {"utc": 1461991194000, "level": 4, "location": "\u65b0\u5317\u5e02\u00b7\u53f0\u7063", "avatar": "http://filestoresg1.beetalkmobile.com:8081/file/165020203579405570", "name": "\u5b971"}, "id": 3620984}
