{"forum": {"content": "\u4ee5\u524d\u8ddf\u670b\u53cb\u73a9\u5916\u62cd\u6642\u62cd\u7684\u2026\ud83d\udc28<br /><br />\u73fe\u5728\u770b\u597d\u597d\u7b11\uff0c\u5176\u5be6\u6211\u662f\u6cf0\u5c71\u2026 \ud83d\ude02 ", "images": ["http://filestoresg1.beetalkmobile.com:8081/file/a6d50490c1540771dc558960273db5a8", "http://filestoresg1.beetalkmobile.com:8081/file/ffb45d4421aabe67439b80f2c60cc029", "http://filestoresg1.beetalkmobile.com:8081/file/730a8f5c535db4eb7ca1da8af9c4c168", "http://filestoresg1.beetalkmobile.com:8081/file/490f3d4bd6e577622b214b25571cb578"], "urls": [], "title": "\u820a\u7167\ud83d\udcf7"}, "threadStatus": 1, "regionId": 886, "barStatus": 0, "barId": 33, "postBy": {"utc": 1457360529000, "level": 3, "location": "", "avatar": "http://filestoresg1.beetalkmobile.com:8081/file/8578968076622020612", "name": "Holiday"}, "id": 3253230}
