{"forum": {"content": "\u677f\u6a4b \u570b\u4e09 \u5929\u880d\ud83c\udf38", "images": ["http://filestoresg1.beetalkmobile.com:8081/file/a579a186e2d2fed189bee34939c51a9a", "http://filestoresg1.beetalkmobile.com:8081/file/181e268a78a6d49550ec16e243dd696f", "http://filestoresg1.beetalkmobile.com:8081/file/0e56e94e15959df6d1d6475fa0dbc7d2"], "urls": [], "title": "\u4e0d\u5982\u6211\u5011\u5148\u4f86\u8a8d\u8b58\u5982\u4f55\ud83d\ude33"}, "threadStatus": 1, "regionId": 886, "barStatus": 0, "barId": 205, "postBy": {"utc": 1461167566000, "level": 5, "location": "\u65b0\u5317\u5e02\u00b7\u53f0\u7063", "avatar": "http://filestoresg1.beetalkmobile.com:8081/file/-7434602950358453495", "name": "\u665e"}, "id": 3555906}
