{"forum": {"content": "\u5feb\u9ede\u4ecb\u7d39\u81ea\u5df1\u8b93\u6211\u4e86\u89e3\u4f60\u5427\uff01", "images": ["http://filestoresg1.beetalkmobile.com:8081/file/e48aae617b11df74806f59689608839a", "http://filestoresg1.beetalkmobile.com:8081/file/c69eaec3959ddc4f1a0786c639bc2d6a", "http://filestoresg1.beetalkmobile.com:8081/file/add9c88f0249b72c80c1be8b0ac2d711", "http://filestoresg1.beetalkmobile.com:8081/file/63d9dcfea6dc5b4ba8345c4125ecb4e0"], "urls": [], "title": "\u75284\u500b\u5b57\u5f62\u5bb9\u4f60\u81ea\u5df1"}, "threadStatus": 0, "regionId": 886, "barStatus": 0, "barId": 205, "postBy": {"utc": 1458797532000, "level": 4, "location": "\u53f0\u5357\u5e02\u00b7\u53f0\u7063", "avatar": "http://filestoresg1.beetalkmobile.com:8081/file/-6500765725092889340", "name": "\ud83d\udc96\ud83d\udca6\ud83d\udc93\u7687\u540e\ud83d\udc93\ud83d\udca6\ud83d\udc96"}, "id": 3367610}
