{"forum": {"content": "\u771f\u7684\u770b\u4e0d\u81a9\u6b38\u54c8\u54c8\ud83d\ude02\ud83d\ude02", "images": ["http://filestoresg1.beetalkmobile.com:8081/file/fdd5936d6a83b8550c99d27daf6eb688"], "urls": [], "title": "\u6703\u9577\u548c\u62c9\u683c\u85a9\u65af\u4f60\u5011\u600e\u9ebc\u4e86"}, "threadStatus": 0, "regionId": 886, "barStatus": 0, "barId": 10, "postBy": {"utc": 1459759866000, "level": 2, "location": "Tainan City\u00b7Taiwan", "avatar": "http://filestoresg1.beetalkmobile.com:8081/file/7833450817336212686", "name": "\u9d7a\u7440"}, "id": 3444265}
