{"forum": {"content": "\u559c\u6b61\u651d\u5f71\u7684\u5f1f\u5144\u59d0\u59b9\uff0c\u53ef\u4ee5\u627e\u6211\u4ea4\u6d41\u7aa9\u3002", "images": ["http://filestoresg1.beetalkmobile.com:8081/file/2ced0c850961c07ee8139489286b331e"], "urls": [], "title": "\u6211\u662f\u9ad8\u4e2d\u751f\uff0c\u6211\u611b\u651d\u5f71\u3002"}, "threadStatus": 0, "regionId": 886, "barStatus": 0, "barId": 438, "postBy": {"utc": 1454383631000, "level": 4, "location": "\u53f0\u4e2d\u5e02\u00b7\u53f0\u7063", "avatar": "http://filestoresg1.beetalkmobile.com:8081/file/3878486587046205186", "name": "\u8fea\u723e\ud83d\udcf8"}, "id": 3024095}
