{"forum": {"content": "\u5e74\u5047\u653e\u5b8c \u7b2c\u4e00\u5929\u4e0a\u73ed\u883b\u61f6\u7684Fu", "images": ["http://filestoresg1.beetalkmobile.com:8081/file/5eb9345482104cccc23f4b34cb7dc711"], "urls": [], "title": "\u662f\u4e0d\u662f\uff1f"}, "threadStatus": 0, "regionId": 886, "barStatus": 0, "barId": 4, "postBy": {"utc": 1455537070000, "level": 3, "location": "", "avatar": "http://filestoresg1.beetalkmobile.com:8081/file/3399879084115561478", "name": "\u264e\ufe0f Ken\u2660\ufe0f"}, "id": 3109154}
