{"forum": {"content": "\u4eca\u5e74\u838a\u656c\u5c0f\u9ad8\u4e00<br />\u60f3\u8a8d\u8b58\u9ad4\u80b2\u73ed\u8ddf\u8868\u85dd\u79d1\u7684\u4eba<br />\u6b61\u8fce\u8a8d\u8b58\u311b", "images": ["http://filestoresg1.beetalkmobile.com:8081/file/460ebb8a19fc39e4f9126852eee922bd", "http://filestoresg1.beetalkmobile.com:8081/file/3f638d7b41ea6ffcbf3228bb18525dd1"], "urls": [], "title": "\u55e8\u55e8"}, "threadStatus": 1, "regionId": 886, "barStatus": 0, "barId": 438, "postBy": {"utc": 1463824986000, "level": 1, "location": "\u65b0\u5317\u5e02\u00b7\u53f0\u7063", "avatar": "http://filestoresg1.beetalkmobile.com:8081/file/1049716961115950607", "name": "\u5446."}, "id": 3763475}
