{"forum": {"content": "\u4e0d\u7136\u6211\u6703\u751f\u6c23\u5594\ud83d\ude21\ud83d\ude21\ud83d\ude21", "images": ["http://filestoresg1.beetalkmobile.com:8081/file/7953b5145b7583c8b71a5a48239f9e18"], "urls": [], "title": "\u8b1b\u8a71\u4e0d\u8981\u50cf\u5403\u5927\u4fbf\u4e00\u6a23\u90a3\u9ebc\u6c92\u6c34\u6e96"}, "threadStatus": 0, "regionId": 886, "barStatus": 0, "barId": 4, "postBy": {"utc": 1456375523000, "level": 2, "location": "\u6843\u5712\u5e02\u00b7\u53f0\u7063", "avatar": "http://filestoresg1.beetalkmobile.com:8081/file/6293890431514906625", "name": "\u67d4"}, "id": 3176011}
