{"forum": {"content": "\u5404\u4f4d\u77e5\u9053\u4eca\u59292/14\u662f\u4ec0\u9ebc\u5927\u65e5\u5b50\u55ce<br />.<br />.<br />.<br />.<br />.<br />.<br />.<br />\u6c92\u932f \u662f\u661f\u671f\u65e5 ", "images": ["http://filestoresg1.beetalkmobile.com:8081/file/116af1a16c5a9cd0429c889c05428787"], "urls": [], "title": "\u4eca\u5929\u662f\u597d\u65e5\u5b50"}, "threadStatus": 0, "regionId": 886, "barStatus": 0, "barId": 10, "postBy": {"utc": 1455410508000, "level": 6, "location": "\u65b0\u7af9\u5e02\u00b7\u53f0\u7063", "avatar": "http://filestoresg1.beetalkmobile.com:8081/file/-2807915198254816765", "name": "Lee"}, "id": 3098746}
