{"forum": {"content": "\u5148\u4ea4\u670b\u53cb\u56c9\uff01<br />\u804a\u5f97\u4f86\u6bd4\u8f03\u91cd\u8981\u2026", "images": ["http://filestoresg1.beetalkmobile.com:8081/file/ff898ea6e0a5e2b13ebe8fb7eb330b49", "http://filestoresg1.beetalkmobile.com:8081/file/39b9c1faf06c6d330491fb499887c779", "http://filestoresg1.beetalkmobile.com:8081/file/b0c7d1eb4b1f244ff75bd354e3c213cc"], "urls": [], "title": "\u771f\u7684\u9084\u6709\u611b\u60c5\u5b58\u5728\u55ce\uff1f"}, "threadStatus": 0, "regionId": 886, "barStatus": 0, "barId": 205, "postBy": {"utc": 1454639851000, "level": 2, "location": "\u53f0\u4e2d\u5e02\u00b7\u53f0\u7063", "avatar": "http://filestoresg1.beetalkmobile.com:8081/file/3011991159405799075", "name": "\u5c0f\u90ed"}, "id": 3042315}
