{"forum": {"content": "me 16y<br />\u4e0a\u8ab2\u6c92\u6642\u9593<br />\u55ae\u8eab\u7121\u804a\u4e86<br />\u6b61\u8fce\u4f86\u8a8d\u8b58<br />\u8b8a\u614b\u5317\u5317\u5c41\u5b69\u52ff\u4f86", "images": ["http://filestoresg1.beetalkmobile.com:8081/file/18113b9053e625509f3ab2c3dff27f7b"], "urls": [], "title": "\u55ae\u8eab\u6b61\u8fce\u965016~20"}, "threadStatus": 0, "regionId": 886, "barStatus": 0, "barId": 205, "postBy": {"utc": 1462959245000, "level": 3, "location": "\u9ad8\u96c4\u5e02\u00b7\u53f0\u7063", "avatar": "http://filestoresg1.beetalkmobile.com:8081/file/9097766037874908721", "name": "\u53ea\u8981\u4e0d\u662f\u9ad8\u96c4\u4e00\u5f8b\u4e0d\u56de"}, "id": 3696678}
