{"forum": {"content": "\u4ee5\u4e0b\u958b\u653e\u9694\u5c64\u7d17\u9694\u5ea7\u5c71\u7684\u5973\u751f", "images": ["http://filestoresg1.beetalkmobile.com:8081/file/2447e2b525f0f311911024035fc2c3fb"], "urls": [], "title": "\u627e\u4e00\u4f4d\u9694\u5c64\u7d17\u7684\u5973\u751f"}, "threadStatus": 1, "regionId": 886, "barStatus": 0, "barId": 774, "postBy": {"utc": 1456716154000, "level": 1, "location": "\u6843\u5712\u5e02\u00b7\u53f0\u7063", "avatar": "http://filestoresg1.beetalkmobile.com:8081/file/-3643290050896082175", "name": "Nichola"}, "id": 3202635}
