{"forum": {"content": "\u60c5\u4eba\u7bc0\u8036 \u9084\u662f\u4e00\u689d\u55ae\u8eab\u72d7\u54c8\u54c8<br />\u6709\u4eba\u8981\u8a8d\u990a\u55ce\ud83d\udc96", "images": ["http://filestoresg1.beetalkmobile.com:8081/file/2f7ebe584a00e3f59d2d73b2a8dd7158"], "urls": [], "title": "\u6709\u597d\u5fc3\u4eba\u8981\u5e36\u8d70\u55ce\ud83d\ude0d"}, "threadStatus": 1, "regionId": 886, "barStatus": 0, "barId": 205, "postBy": {"utc": 1455460344000, "level": 2, "location": "\u82b1\u84ee\u7e23\u00b7\u53f0\u7063", "avatar": "http://filestoresg1.beetalkmobile.com:8081/file/7677769850817668055", "name": "Hao"}, "id": 3103819}
