{"forum": {"content": "ORGANIK 2016 \u6709\u6a5f\u82b1\u84ee\u97f3\u6a02\u796d", "images": [], "urls": [{"url": "https://vimeo.com/165595701?ref=fb-share&1", "thumbUrl": "https://i.vimeocdn.com/video/569502449_1280x720.jpg", "description": "An event video for Organik 2016 \u2014 a beach-side music festival presented by Smoke Machine in Huting, ", "title": "Organik Festival 2016"}], "title": "\u6d17\u6ecc\u5fc3\u9748\u7684\u6709\u6a5f\u4e4b\u65c5"}, "threadStatus": 0, "regionId": 886, "barStatus": 0, "barId": 54, "postBy": {"utc": 1462796713000, "level": 2, "location": "\u65b0\u5317\u5e02\u00b7\u53f0\u7063", "avatar": "http://filestoresg1.beetalkmobile.com:8081/file/-4612111524613811710", "name": "\u67d4\u6d3e\u7537\u5b50"}, "id": 3683706}
