{"forum": {"content": "\u72c0\u6cc1\u9084ok \u91e3\u4e86 \u4e00\u500b\u5c0f\u6642\u534a \u8d77\u4f86 2 P \u8dd1\u6389 \u5169P \u90fd\u662f\u5feb3\u65a4 \u86af\u8693\u5e36\u4e86100\u591ap", "images": ["http://filestoresg1.beetalkmobile.com:8081/file/c33645114c06ae3643c2dd93c1e86cb6", "http://filestoresg1.beetalkmobile.com:8081/file/cc0e2189b2c55c530b74225f8fd8a157", "http://filestoresg1.beetalkmobile.com:8081/file/38b0bf65960f308fb599c6d2a5b21a18"], "urls": [], "title": "\u6628\u5929\u53bb\u5927\u809a\u6eaa\u91e3\u9b5a"}, "threadStatus": 0, "regionId": 886, "barStatus": 0, "barId": 723, "postBy": {"utc": 1461630216000, "level": 0, "location": "\u53f0\u4e2d\u5e02\u00b7\u53f0\u7063", "avatar": "http://filestoresg1.beetalkmobile.com:8081/file/-6110314859877850990", "name": "\u5289\u661f\u4eae"}, "id": 3593350}
