{"forum": {"content": "\u5915\u967d\u8a66\u62cd<br />\u6b61\u8fce\u6307\u6559", "images": ["http://filestoresg1.beetalkmobile.com:8081/file/5077321db4846c8099c5d9fe0dd2c59a", "http://filestoresg1.beetalkmobile.com:8081/file/fb96c85baf2fa7318083a39a0dbbc609", "http://filestoresg1.beetalkmobile.com:8081/file/b46582e9172d2da8001221d3d8c52bda", "http://filestoresg1.beetalkmobile.com:8081/file/71381bfdee39517ecfaefce291287845", "http://filestoresg1.beetalkmobile.com:8081/file/327c95b6e0b12a9f9e6ee3062ebecdc3", "http://filestoresg1.beetalkmobile.com:8081/file/78ac9e78c31c805a05d8d7cf71b163d4"], "urls": [], "title": "\u5915\u967d"}, "threadStatus": 0, "regionId": 886, "barStatus": 0, "barId": 77, "postBy": {"utc": 1462717873000, "level": 9, "location": "\u53f0\u4e2d\u5e02\u00b7\u53f0\u7063", "avatar": "http://filestoresg1.beetalkmobile.com:8081/file/-1238168836745204421", "name": "Sho Kao"}, "id": 3677680}
