{"forum": {"content": "175/57/16/\u81fa\u5317\u4eba ", "images": ["http://filestoresg1.beetalkmobile.com:8081/file/b8afde77b9a37097816b16710648cf4c"], "urls": [], "title": "\u6211\u662f\u96d9\u6027\u6069\u2026\u2026"}, "threadStatus": 0, "regionId": 886, "barStatus": 0, "barId": 205, "postBy": {"utc": 1464462165000, "level": 1, "location": "\u65b0\u5317\u5e02\u00b7\u53f0\u7063", "avatar": "http://filestoresg1.beetalkmobile.com:8081/file/-336977221283127104", "name": "\u5947\u5947"}, "id": 3811988}
