{"forum": {"content": "\u91e3\u6cd5\uff1a\u98c4\u6d6e\u8ce4\u91e3<br />\u990c\uff1a\u767d\u571f\u53f8(\u81ea\u5df1\u4e5f\u53ef\u4ee5\u5403)", "images": ["http://filestoresg1.beetalkmobile.com:8081/file/6afb29b768a489cc31a29cd503784eb6", "http://filestoresg1.beetalkmobile.com:8081/file/211776624a9b4e0750f107403ac86229", "http://filestoresg1.beetalkmobile.com:8081/file/6a8e3e41cc382d5e23bf309cda8586b9"], "urls": [], "title": "\u57fa\u9686\u6cb3\u8349\u9b5a\u90e8\u968a"}, "threadStatus": 0, "regionId": 886, "barStatus": 0, "barId": 723, "postBy": {"utc": 1465973664000, "level": 11, "location": "\u53f0\u5317\u5e02\u00b7\u53f0\u7063", "avatar": "http://filestoresg1.beetalkmobile.com:8081/file/7406236664641867926", "name": "\u5f35\u5cf0\u57ce"}, "id": 3923343}
