{"forum": {"content": "\u6211\u662f\u53f0\u6771\u6210\u529f\u67d0\u90e8\u843d\u7684\u554a\u7f8e\u65cf\u5c0f\u5973\u5b69\ud83d\ude0c\ud83d\ude0c<br />\u6211\u76ae\u819a\u4e0d\u767d\u8eab\u9ad8\u4e0d\u77ee\u9152\u91cf\u4e0d\u81f3\u65bc\u6d77\u91cf\ud83d\ude00\ud83d\ude00<br />\u4f46\u6211\u71b1\u611b\u4ea4\u670b\u53cb\u500b\u6027\u5927\u524c\u524c\u6beb\u7121\u5f62\u8c61\ud83d\ude33\ud83d\ude33<br />\u5e0c\u671b\u53ef\u4ee5\u8ddf\u4f60\u5011\u505a\u670b\u53cb\u751a\u81f3\u8a8d\u8b58\u66f4\u591a\u539f\u4f4f\u6c11\u55b2\uff5e<br />#86/12/16\u5c04\u624b\u599e", "images": ["http://filestoresg1.beetalkmobile.com:8081/file/63d045f5a672d82ff61eeeccd0756ff5"], "urls": [], "title": "\u53f0\u6771-\u554a\u7f8e\u65cf"}, "threadStatus": 0, "regionId": 886, "barStatus": 0, "barId": 727, "postBy": {"utc": 1465589755000, "level": 2, "location": "\u6843\u5712\u5e02\u00b7\u53f0\u7063", "avatar": "http://filestoresg1.beetalkmobile.com:8081/file/-5560855905294290360", "name": "Amis\u2764"}, "id": 3893744}
