{"forum": {"content": "\u4f86\u804a\u5929\u8a8d\u8b58\u963f\u6211\u597d\u7121\u804a\uff0c\u4e5f\u53ef\u4ee5\u52a0\u6211fb\u311b", "images": ["http://filestoresg1.beetalkmobile.com:8081/file/6f0971129a4cdc14e23fad915c39baa0", "http://filestoresg1.beetalkmobile.com:8081/file/5ffc36148a204daafa8bc03caa2ce4af", "http://filestoresg1.beetalkmobile.com:8081/file/6f59f94a3da9539460adcff5de350958", "http://filestoresg1.beetalkmobile.com:8081/file/199f086e888f5cb042ea2217941f04c6"], "urls": [], "title": "\u8a8d\u8b58"}, "threadStatus": 0, "regionId": 886, "barStatus": 0, "barId": 512, "postBy": {"utc": 1464877301000, "level": 2, "location": "\u9ad8\u96c4\u5e02\u00b7\u53f0\u7063", "avatar": "http://filestoresg1.beetalkmobile.com:8081/file/7808690900631663524", "name": "\u5475\u5475"}, "id": 3841976}
