{"forum": {"content": "\u7537\u4eba  \u4f60\u62fc\u4e86\u55ce<br />\u6709\u62ff\u51fa\u6c23\u9b44\u4e86\u55ce\uff01<br /><br />http://mp.weixin.qq.com/s?__biz=MzA5ODAzNTEyMQ==&mid=402825477&idx=2&sn=eb6e58282808e1096c1842a18bf57520&scene=1&srcid=0412K19NMWyDbQDAYSPbitC5&from=groupmessage&isappinstalled=0#wechat_redirect", "images": ["http://filestoresg1.beetalkmobile.com:8081/file/3b4fa7ebdcdaee7838828ab4c546162c"], "urls": [], "title": "\u7537\u4eba \u597d\u6587\u5206\u4eab"}, "threadStatus": 1, "regionId": 886, "barStatus": 2, "barId": 732, "postBy": {"utc": 1460475636000, "level": 1, "location": "\u9ad8\u96c4\u5e02\u00b7\u53f0\u7063", "avatar": "http://filestoresg1.beetalkmobile.com:8081/file/-1394816247027935371", "name": "Yung Jie"}, "id": 3502068}
