{"forum": {"content": "\u71b1\u611b\u51fa\u9580\u6563\u6b65\u7684\u6cf1\u6cf1^_^<br /><br />\u5341\u500b\u6708\u4e86\uff0c<br /><br />\u4e00\u5e74\u56db\u5b63\u4e0d\u9593\u65b7\u3002", "images": ["http://filestoresg1.beetalkmobile.com:8081/file/a2acef5b26da43c6836e02945d9708a4", "http://filestoresg1.beetalkmobile.com:8081/file/9b0e0b957e10a0f77f5b8a37872fbd94", "http://filestoresg1.beetalkmobile.com:8081/file/368c9a0a1cbded70425aaca84fd10e33", "http://filestoresg1.beetalkmobile.com:8081/file/7a98ec85fb72298192dfa5d4cee2f4ce", "http://filestoresg1.beetalkmobile.com:8081/file/495c2680e1ea1bb417457d8100bb2113", "http://filestoresg1.beetalkmobile.com:8081/file/46f674cc6ced450b020dbdf5401b3f3a"], "urls": [], "title": "\u6bcf\u5929\u90fd\u8981\u6563\u6b65\u5594\uff5e"}, "threadStatus": 0, "regionId": 886, "barStatus": 0, "barId": 712, "postBy": {"utc": 1460482660000, "level": 1, "location": "\u53f0\u5357\u5e02\u00b7\u53f0\u7063", "avatar": "http://filestoresg1.beetalkmobile.com:8081/file/5584654858844016387", "name": "Daddy Wythe"}, "id": 3502818}
