{"forum": {"content": "\u4f4f\u9ad8\u96c4\u534a\u5e74\uff0c\u6c92\u6709\u5e7e\u500b\u670b\u53cb<br />\u6709\u4eba\u9858\u610f\u8a8d\u8b58\u55ce?", "images": ["http://filestoresg1.beetalkmobile.com:8081/file/7e7dcc06302e02783cb5d8a2f67dc894"], "urls": [], "title": "40\u6b72\u4e86\uff0c\u6709\u4eba\u8981\u55ce?"}, "threadStatus": 1, "regionId": 886, "barStatus": 0, "barId": 208, "postBy": {"utc": 1455560735000, "level": 1, "location": "\u9ad8\u96c4\u5e02\u00b7\u53f0\u7063", "avatar": "http://filestoresg1.beetalkmobile.com:8081/file/-4505213695726012056", "name": "\u5c0fa"}, "id": 3111879}
