{"forum": {"content": "\u8ab0\u8981\u804a\u5929\ud83d\ude2c\uff1f", "images": ["http://filestoresg1.beetalkmobile.com:8081/file/a308f66e62d1f7065b0c3edb968cadda", "http://filestoresg1.beetalkmobile.com:8081/file/4f8c4e91453d4238359711f93a4d0d60", "http://filestoresg1.beetalkmobile.com:8081/file/3f1f7d8f95422b4ecdc2b82e847dcfbe"], "urls": [], "title": "\u55e8\ud83d\udc4b"}, "threadStatus": 1, "regionId": 886, "barStatus": 0, "barId": 4, "postBy": {"utc": 1454920314000, "level": 1, "location": "\u9ad8\u96c4\u5e02\u00b7\u53f0\u7063", "avatar": "http://filestoresg1.beetalkmobile.com:8081/file/7296370172274630144", "name": "J"}, "id": 3061421}
