{"forum": {"content": "\u660e\u59296/8<br />10:00~13:00\u6709\u4eba\u6709\u7a7a\u62cd\u7167\u55ce<br />\u98a8\u683c\u90fd\u53ef\u8ac7", "images": ["http://filestoresg1.beetalkmobile.com:8081/file/6e9fcbda48bfffd90d970e8af558b301"], "urls": [], "title": "\u6025\u5fb5\u4e92\u60e0\u651d\u5f71\u5e2b"}, "threadStatus": 1, "regionId": 886, "barStatus": 0, "barId": 77, "postBy": {"utc": 1465232084000, "level": 2, "location": "\u65b0\u5317\u5e02\u00b7\u53f0\u7063", "avatar": "http://filestoresg1.beetalkmobile.com:8081/file/2551149552608430345", "name": "\ud83d\ude1c\ud83d\ude1c\ud83d\ude1c"}, "id": 3867820}
