{"forum": {"content": "\u627e\u4f34\u804a\u5929", "images": ["http://filestoresg1.beetalkmobile.com:8081/file/d9b3fa5518e666bc1f27f9aa333d5d8a", "http://filestoresg1.beetalkmobile.com:8081/file/903f650c00c88769ac9196b7e5fc93a6"], "urls": [], "title": "\u627e\u4f34"}, "threadStatus": 1, "regionId": 886, "barStatus": 0, "barId": 205, "postBy": {"utc": 1461081647000, "level": 2, "location": "\u5f70\u5316\u7e23\u00b7\u53f0\u7063", "avatar": "http://filestoresg1.beetalkmobile.com:8081/file/-3399658065955946082", "name": "\u8449\u5e0c"}, "id": 3548820}
